kibo_pgar_lib/__init__.py
kibo_pgar_lib/ansi_colors.py
kibo_pgar_lib/file_service.py
kibo_pgar_lib/input_data.py
kibo_pgar_lib/known_problems.py
kibo_pgar_lib/menu.py
kibo_pgar_lib/pretty_strings.py
kibo_pgar_lib/pretty_tables.py
kibo_pgar_lib/random_draws.py
kibo_pgar_lib-1.4.0.dist-info/LICENSE.txt
kibo_pgar_lib-1.4.0.dist-info/METADATA
kibo_pgar_lib-1.4.0.dist-info/WHEEL
kibo_pgar_lib-1.4.0.dist-info/top_level.txt
kibo_pgar_lib-1.4.0.dist-info/RECORD
