Metadata-Version: 2.2
Name: kibo_pgar_lib
Version: 1.4.0
Summary: KiboUniBSFpLib modified, documented and converted in python.
Home-page: https://github.com/AlessandroMuscio/kibo_pgar_lib
Author: Alessandro Muscio
Author-email: Alessandro Muscio <a.muscio001@studenti.unibs.it>
License: MIT License
Project-URL: source, https://github.com/AlessandroMuscio/kibo_pgar_lib
Project-URL: download, https://pypi.org/project/kibo-unibs-fp-lib/#files
Project-URL: tracker, https://github.com/AlessandroMuscio/kibo_pgar_lib/issues
Classifier: Development Status :: 5 - Production/Stable
Classifier: Intended Audience :: Developers
Classifier: License :: OSI Approved :: MIT License
Classifier: Programming Language :: Python
Classifier: Programming Language :: Python :: 3
Classifier: Programming Language :: Python :: 3.12
Classifier: Typing :: Typed
Classifier: Operating System :: OS Independent
Requires-Python: >=3.9
License-File: LICENSE.txt
Dynamic: author
Dynamic: home-page
